setup.cfg
setup.py
Mongothon3.egg-info/PKG-INFO
Mongothon3.egg-info/SOURCES.txt
Mongothon3.egg-info/dependency_links.txt
Mongothon3.egg-info/pbr.json
Mongothon3.egg-info/requires.txt
Mongothon3.egg-info/top_level.txt
mongothon/__init__.py
mongothon/document.py
mongothon/events.py
mongothon/exceptions.py
mongothon/model.py
mongothon/queries.py
mongothon/schema.py
mongothon/scopes.py
mongothon/validators.py