Metadata-Version: 1.0
Name: Mongothon3
Version: 0.7.20
Summary: A MongoDB object-document mapping layer for Python
Home-page: http://github.com/thekiba/mongothon3
Author: Tom Leach
Author-email: tom@gc.io
License: BSD
Keywords: mongo mongodb database pymongo odm validation
Platform: UNKNOWN
